<sburb description='cronus dialogs'>
	<classes>
		<action sprite='karkat' class='tereziTalk1' command='talk' name='テレジと話す'>
      <args>
      @karkat_talk カーカット: テレジ、ここで何してるんだ？眠ってたか知らなかった。
      @terezi_idle テレジ: ３あ
      @karkat_talk カーカット: なんで森で一人ぼっちにいるんだ？いや、偽の森でな。
      @karkat_what カーカット: そしてなんでそんな風にドラゴン着ぐるみが下げているのか？どうした？
      @terezi_idle テレジ: １や
      @terezi_idle テレジ: 大丈夫だ
      @karkat_yell カーカット: 大丈夫らしくねーよ。オレにウソをつくな、オマエが困ってるときわかるぞ。
      @terezi_idle テレジ: カーカット放ってお１てくれ
      @karkat_sullen カーカット: ああ、一人の時間欲しかったらわかる。だって、実際オレ自身が剝れやめたばかりだ。
      @karkat_talk カーカット: でも誰かに話すのは助けになる。オレと何でも話せるよ、わかるだろう？
      @terezi_idle テレジ: うん、わかるね
      @karkat_yell カーカット: デイブのことか？アイツまた嫌なことしたのか？
      @terezi_idle テレジ: ...
      @karkat_shout カーカット: オマエと別れた？別れただろうな。やはり、そういう予感がし...
      @terezi_idle テレジ: 別れなかった４！！！
      @terezi_idle テレジ: デ１ブと関係な１んだ
      @karkat_what カーカット: それで何だよ
      @terezi_idle テレジ: わた４の
      @terezi_idle テレジ: 先祖のことだ
      @karkat_eyeroll1 カーカット: そう？アイツは？
      @terezi_idle テレジ: ラテュラ
      @terezi_idle テレジ: ただ
      @terezi_idle テレジ: すごく
      @terezi_sad テレジ: １か４てる >:[
      @karkat_eyeroll1 カーカット: はぁ？
      @terezi_idle テレジ: そんなに１かせるなんて
      @terezi_idle テレジ: 可能だと知らなかった
      @terezi_sad テレジ: ほぼ我慢できな１４　カーカット
      @terezi_sad テレジ: そのかっこ４３
      @terezi_idle テレジ: あ１つどうやってできるの？
      @karkat_eyeroll2 カーカット: まあ、どうかな。クソスケボーを乗れる。それは一応説明終わりだな。
      @terezi_sad テレジ: それ４りもずっとあると思う
      @terezi_sad テレジ: 誰もラテュラのこと大好きだ４
      @terezi_sad テレジ: 生意気盛りで楽４くて、ゲームで最強で、スタントがすべて素晴ら４くて
      @terezi_idle テレジ: わた４どうやってメガネにかなう？
      @karkat_facepalm カーカット: ああ勘弁してくれよ
      @karkat_idle カーカット: これからはオマエがそういうことをするなんて言わないで。
      @terezi_idle テレジ: 何のこと？
      @karkat_idle カーカット: 自尊心のことだ。
      @karkat_talk カーカット: オマエは本当にそういう気持ち要らない、マジで不当だ。
      @terezi_idle テレジ: でもわた４はそう１う気分だから、残念だ！！！
      @karkat_yell カーカット: テレジ、これを十分に強調できない。オマエは誰もの影にいないんだ。
      @karkat_talk カーカット: オレラの先祖について教えてやる。
      @karkat_shout カーカット: 全員クソ野郎だ！！！
      @terezi_idle テレジ: >:|
      @terezi_idle テレジ: ラテュラってクソ野郎じゃな１４
      @karkat_talk カーカット: いや、本当だ。信じて。
      @karkat_talk カーカット: 全員がそうだ。少なくとも大部分だ。
      @karkat_shout カーカット: 一応人なんてないよ。歩いている、しゃべってる、まあ...
      @karkat_yell カーカット: どうやって言うべきか分かんない。ひどい決まりきった行動パターンの生きたパロディだ。
      @terezi_idle テレジ: え、ってう１か...
      @terezi_idle テレジ: テ１ーンエ１ジャー３た１に？
      @karkat_eyeroll2 カーカット: そう。
      @karkat_talk カーカット: でもそれだけじゃない。例えばオレの先祖ね。
      @karkat_yell カーカット: 全くクソ野郎だ！もっともクソな野郎かもしれない。
      @karkat_yell カーカット: オレみたいにみんなに怒鳴らないからすぐにわかるはずじゃない？でもそりゃより悪くするかも。
      @karkat_shout カーカット: 偽善的で理解不能なナンセンスを延々と語り続けるんだ。誰よりも優れていると思い込んでいるくせに、それを偽の超学究的な謙遜で飾り立てている。「問題」を抱えたヤツを擁護しようとするが、結局は皮肉な形で侮辱するだけだ。延々と説教するばかりで、友人を「擁護」しようとすると、たいてい暗に批判的な態度で悪口するんだ。
      @karkat_talkカーカット: 本当に永遠に語り続けたいけど、そうしないとアイツのレベルに落ちてしまうからやめる。
      @terezi_idle テレジ: へへ...
      @karkat_eyeroll2 カーカット: オマエの先祖か？ああ、たしか"楽しい"な。でもすごいまやかしだな。
      @karkat_shout カーカット: ああ、また誰か何か言っても構わない、嗅覚がなくなったらホントの障害じゃねーよ！！！
      @karkat_talk カーカット: そのクールガールは明らかな演技だ。完璧にこなすために何周期も努力を重なて、それによって得られる注目を大いに喜んでる様子も見て取れる。
      @karkat_talk カーカット: だがアイツはそんなに努力してるからこそ何も心配要らないんだ。
      @karkat_talk カーカット: いい人になるため努力なんて要らない。
      @karkat_sullen カーカット: ほら、オマエはもう、ありのままの自分でいるだけで楽しくて好かれ方を知っているはず。人に好印象を与えるために、大げさな真似をする必要はない。ラテュラの「かっこいい女の子」演技は、まるで変装のようで、自分のどこかに不満がある部分を隠してるのだろう。でもオマエがそんな風に自分を引っ込んだら、実は、すでにステキなオマエを隠してるんだ。
      @terezi_idle テレジ: ...
      @karkat_facepalm カーカット: オレラの関係をもうやっちまったとわかってる。これは、ええ...よし。自分を償おうにしてるわけじゃないよ。これは因果応報だ。それを受け止めた。でもオマエの友達としてこんな浅はかで二次元的なバカどものせいで、自分を責め始めるなんて本当に嫌だ。でも、オレについて自分で選んだことは認めるし、その決断を尊重する。ただ、幸せになってほしいだけ。
      @karkat_eyeroll2 カーカット: OK、たぶんもう一度藪蛇になってしまったしオマエを煙たくにしてるかも。そろそろ部屋に戻ろうか。オレが言ったこと少しだけ真剣に受け止めたらいいけど。
      @karkat_eyeroll1 カーカット: ああ。うん。それで、じゃ。
      <!--  -->
      </args>
</action>

<action sprite='meenah' class='tereziTalk2' command='talk' name='テレジと話す'>
      <args>
      @meenah_idle ミーナ: ちなみにアンタのドラゴン着ぐるみって最高だ
      @terezi_idle テレジ: >:]
      </args>
</action>
	</classes>
</sburb>
